anrt_checker/__init__.py
anrt_checker/__main__.py
anrt_checker/lib.py
anrt_checker-1.0.1.dist-info/LICENSE
anrt_checker-1.0.1.dist-info/METADATA
anrt_checker-1.0.1.dist-info/WHEEL
anrt_checker-1.0.1.dist-info/top_level.txt
anrt_checker-1.0.1.dist-info/RECORD
