Metadata-Version: 2.1
Name: anrt-checker
Version: 1.0.1
Summary: A simple tool to check the ANRT website
Author-email: n4n5 <its.just.n4n5@gmail.com>
License: MIT License
Project-URL: Homepage, https://github.com/its-just-nans/anrt-checker
Project-URL: Bug Tracker, https://github.com/its-just-nans/anrt-checker/issues
Keywords: html,index
Classifier: License :: OSI Approved :: MIT License
Classifier: Programming Language :: Python
Classifier: Programming Language :: Python :: 3
Requires-Python: >=3.6
License-File: LICENSE
